{
  "UserConfig": {
    "Namespaces": [
      {
        "Name": "local",
        "Queues": [
          {
            "Name": "ingestion-events",
            "Properties": {
              "DeadLetteringOnMessageExpiration": false,
              "DefaultMessageTimeToLive": "PT1H",
              "DuplicateDetectionHistoryTimeWindow": "PT20S",
              "ForwardDeadLetteredMessagesTo": "",
              "ForwardTo": "",
              "LockDuration": "PT1M",
              "MaxDeliveryCount": 3,
              "RequiresDuplicateDetection": false,
              "RequiresSession": false
            }
          }
        ],
        "Topics": [
          {
            "Name": "aggregate-updates",
            "Properties": {
              "DefaultMessageTimeToLive": "PT1H",
              "DuplicateDetectionHistoryTimeWindow": "PT20S",
              "RequiresDuplicateDetection": false
            },
            "Subscriptions": [
              {
                "Name": "aggregator-sub",
                "Properties": {
                  "DeadLetteringOnMessageExpiration": false,
                  "DefaultMessageTimeToLive": "PT1H",
                  "LockDuration": "PT1M",
                  "MaxDeliveryCount": 3,
                  "RequiresSession": false
                }
              }
            ]
          },
          {
            "Name": "cached-aggregate-updates",
            "Properties": {
              "DefaultMessageTimeToLive": "PT1H",
              "DuplicateDetectionHistoryTimeWindow": "PT20S",
              "RequiresDuplicateDetection": false
            },
            "Subscriptions": [
              {
                "Name": "signalr-sub",
                "Properties": {
                  "DeadLetteringOnMessageExpiration": false,
                  "DefaultMessageTimeToLive": "PT1H",
                  "LockDuration": "PT1M",
                  "MaxDeliveryCount": 3,
                  "RequiresSession": false
                }
              }
            ]
          }
        ]
      }
    ],
    "Logging": {
      "Type": "File"
    }
  }
}
